jup_python_sdk/__init__.py
jup_python_sdk/clients/__init__.py
jup_python_sdk/clients/jupiter_client.py
jup_python_sdk/clients/ultra_api_client.py
jup_python_sdk/models/__init__.py
jup_python_sdk/models/common/__init__.py
jup_python_sdk/models/common/dex_enum.py
jup_python_sdk/models/ultra_api/__init__.py
jup_python_sdk/models/ultra_api/ultra_execute_request_model.py
jup_python_sdk/models/ultra_api/ultra_order_request_model.py
jup_python_sdk-1.1.0.dist-info/LICENSE
jup_python_sdk-1.1.0.dist-info/METADATA
jup_python_sdk-1.1.0.dist-info/WHEEL
jup_python_sdk-1.1.0.dist-info/RECORD
