Metadata-Version: 2.3
Name: jup-python-sdk
Version: 1.1.0
Summary: Python SDK for Jupiter Exchange APIs.
License: MIT
Keywords: solana,jupiter,sdk
Author: Fiji
Author-email: charismoutafidis@gmail.com
Requires-Python: >=3.9,<4.0
Classifier: License :: OSI Approved :: MIT License
Classifier: Operating System :: OS Independent
Classifier: Programming Language :: Python :: 3
Classifier: Programming Language :: Python :: 3.9
Classifier: Programming Language :: Python :: 3.10
Classifier: Programming Language :: Python :: 3.11
Classifier: Programming Language :: Python :: 3.12
Classifier: Programming Language :: Python :: 3.13
Requires-Dist: base58 (>=2.1.1,<3.0.0)
Requires-Dist: httpx (>=0.28.1,<0.29.0)
Requires-Dist: pydantic (>=2.11.3,<3.0.0)
Requires-Dist: solana (>=0.36.6,<0.37.0)
Requires-Dist: solders (>=0.26.0,<0.27.0)
Project-URL: Homepage, https://github.com/Jupiter-DevRel/jup-python-sdk
Project-URL: Repository, https://github.com/Jupiter-DevRel/jup-python-sdk
